localizedpydantic/__init__.py
localizedpydantic/models/__init__.py
localizedpydantic/models/brazil.py
localizedpydantic/validators/__init__.py
localizedpydantic/validators/brazil.py
tests/__init__.py
tests/test_brasil.py
localizedpydantic-0.3.0.dist-info/METADATA
localizedpydantic-0.3.0.dist-info/WHEEL
localizedpydantic-0.3.0.dist-info/top_level.txt
localizedpydantic-0.3.0.dist-info/RECORD
