Metadata-Version: 2.1
Name: localizedpydantic
Version: 0.3.0
Summary: Library to validate localized data with pydantic
Home-page: https://github.com/lucasbalieiro/localizedpydantic
Author: Lucas Balieiro Matos
Author-email: lucasbalieirom@hotmail.com
Classifier: Development Status :: 3 - Alpha
Classifier: Intended Audience :: Developers
Classifier: License :: OSI Approved :: MIT License
Classifier: Operating System :: OS Independent
Classifier: Programming Language :: Python :: 3.7
Classifier: Programming Language :: Python :: 3.8
Classifier: Programming Language :: Python :: 3.9
Classifier: Programming Language :: Python :: 3.10
Requires-Python: >=3.7
Requires-Dist: pydantic
Requires-Dist: requests
